pinaca/__init__.py
pinaca/translation.py
pinaca-0.0.1.dist-info/LICENSE
pinaca-0.0.1.dist-info/METADATA
pinaca-0.0.1.dist-info/WHEEL
pinaca-0.0.1.dist-info/top_level.txt
pinaca-0.0.1.dist-info/RECORD
