Metadata-Version: 2.1
Name: pinaca
Version: 0.0.1
Summary: Python SDK for Pinaca Lab's APIs.
Home-page: https://github.com/Pinaca-Labs/pinaca-python-sdk
Author: BEDAPUDI PRANEETH
Author-email: praneeth@pinacalabs.com
License: MIT
Platform: UNKNOWN
Classifier: License :: OSI Approved :: MIT License
Classifier: Programming Language :: Python
Classifier: Programming Language :: Python :: 3
Classifier: Programming Language :: Python :: 3.6
Classifier: Programming Language :: Python :: Implementation :: CPython
Classifier: Programming Language :: Python :: Implementation :: PyPy
Requires-Python: >=3.6.0
Requires-Dist: requests
